feature_generate/__init__.py
feature_generate/calculate_transaction_features.py
feature_generate/categorical_processing.py
feature_generate/feature_processing.py
feature_generate/feature_selection.py
feature_generate/model_training.py
feature_generate/numerical_processing.py
feature_generate/pipeline.py
feature_generate/run_training.py
feature_generate/stratification_processing.py
feature_generate/time_processing.py
feature_generate/train_catboost.py
feature_generate/transaction_processing.py
feature_generate/utils.py
feature_generate/zipcode_processing.py
feature_generate/core/__init__.py
feature_generate/core/business_rules.py
feature_generate/core/categorical_processing.py
feature_generate/core/feature_encoding.py
feature_generate/core/feature_engineering.py
feature_generate/core/feature_selection.py
feature_generate/core/model_training.py
feature_generate/core/numerical_processing.py
feature_generate/core/stratification_processing.py
feature_generate/core/time_processing.py
feature_generate/core/transaction_processing.py
feature_generate/core/transation_processing.py
feature_generate/core/zipcode_processing.py
feature_generate-0.2.7.dist-info/METADATA
feature_generate-0.2.7.dist-info/WHEEL
feature_generate-0.2.7.dist-info/top_level.txt
feature_generate-0.2.7.dist-info/RECORD
