Metadata-Version: 2.4
Name: feature-generate
Version: 0.2.7
Summary: Feature generation tools
Author: Your Name
License: MIT
Classifier: Programming Language :: Python :: 3
Requires-Python: >=3.7
